monocle_googlemap-0.1.2.dist-info/metadata.json
monocle_googlemap-0.1.2.dist-info/WHEEL
monocle_googlemap-0.1.2.dist-info/METADATA
monocle_googlemap-0.1.2.dist-info/top_level.txt
monocle_googlemap-0.1.2.dist-info/DESCRIPTION.rst
monocle_googlemap-0.1.2.dist-info/RECORD
monocle_googlemap/widgets.py
monocle_googlemap/__init__.py
monocle_googlemap/models.py
monocle_googlemap/monocle.py
monocle_googlemap/admin.py
monocle_googlemap/templates/monocle_googlemap/monocle_googlemap.html
monocle_googlemap/fixtures/monocle_googlemap.json
monocle_googlemap/static/monocle_googlemap/monocle_googlemap.css
monocle_googlemap/static/monocle_googlemap/monocle_googlemap.js
